{
  "publicPath": "https://file.calibur.tv/mahoo/",
  "all": [
    "../server/index.spa.html",
    "../server/index.ssr.html",
    "167d78ad99424d98b51e.js",
    "194d6d3190db6cf265a6.css",
    "1ada9ac4a6dc423f349c.css",
    "1ee040b085a25cb3464d.css",
    "1ff0fb24d25d02fdeabe.css",
    "21cf505805bdc654e891.js",
    "2514654ede1fd9e104e0.js",
    "260661d3f48f9818cf18.css",
    "2a3522d2a15d9e7fd931.js",
    "2e9cd71b4c8c2b9ad14b.css",
    "364512dc91e3e0e1aba3.js",
    "38c63ba898531016d18a.js",
    "3bdfb1df616a2088c1e0.js",
    "3c90638fb88082924255.css",
    "3e84bcbcd7b696fc4bce.js",
    "3ed82418b90dc01f96ab.js",
    "41124400a83eb525bf08.css",
    "41447c85a721a262fdf3.css",
    "41930581842131e1a7b4.css",
    "4f3af7b1416f84e0993c.js",
    "519b514a5142cbcda7f2.css",
    "53b450142a73ee15f8c8.css",
    "5986e145044345e6c177.js",
    "60ca2f01a3bb42a37afd.js",
    "69a9310a23e4b5bdfce5.js",
    "6a4c5aaeb73cf6bcf55c.js",
    "6c26467d8747cadc9f72.js",
    "6c47a4814f024403dcf8.js",
    "6ec4fc0ad7da175fbecb.js",
    "7acfd853541d5d7de088.css",
    "7e355d2b4c4b882de518.css",
    "806d72eacac364467d2e.js",
    "82762eab4e0b76c824cd.js",
    "84d4c5b761a621c85f48.js",
    "8f76b6a6cab17477c199.js",
    "9321f089468f18f11bcc.js",
    "97ed3fece637d1817c42.js",
    "9838e61d4d4339123f56.css",
    "9b5ac897b6e312ca3b3e.js",
    "9d8df1aaaebec64c8a4a.js",
    "LICENSES",
    "a2ff013f19a2146052b0.css",
    "a8dc3cbaac32c132503f.css",
    "a9c17e539311cf11685b.js",
    "ab007b2500947025e7c1.css",
    "adcf20a20d1e87ecdf3e.css",
    "afe0bd625ff33229d8e2.js",
    "b7efb54a288f62fa5445.js",
    "b981d5fe45fdce2a6166.js",
    "cfa2799ae68d5b22093b.js",
    "d2fcb46e72676b04fa23.css",
    "dbcfad97392035709626.js",
    "de5e88fdeb5a0842cfa3.css",
    "e0b32861eb489a3140f8.js",
    "e7ff0adad236afbe0b9e.js",
    "e92bfdb268501f7326fc.js",
    "f5f07ee40fbcb9e9b140.css",
    "f9bbd441c58078122b28.js",
    "fbd0f0a2e9822524902b.js",
    "fc5064f3dcadd04e6c05.css",
    "fd04783ae2193ca97543.css",
    "fd9359542e040e7aa866.css",
    "ff54f688e77a167f7b9d.js",
    "fonts/535877f.woff",
    "fonts/732389d.ttf",
    "img/04ec302.png",
    "img/324edea.png",
    "img/adea640.jpeg",
    "img/b07f58f.jpeg",
    "img/d465ab1.jpeg",
    "img/e82d3e7.png"
  ],
  "initial": [
    "6c47a4814f024403dcf8.js",
    "2514654ede1fd9e104e0.js",
    "1ff0fb24d25d02fdeabe.css",
    "82762eab4e0b76c824cd.js",
    "194d6d3190db6cf265a6.css",
    "806d72eacac364467d2e.js"
  ],
  "async": [
    "167d78ad99424d98b51e.js",
    "1ada9ac4a6dc423f349c.css",
    "1ee040b085a25cb3464d.css",
    "21cf505805bdc654e891.js",
    "260661d3f48f9818cf18.css",
    "2a3522d2a15d9e7fd931.js",
    "2e9cd71b4c8c2b9ad14b.css",
    "364512dc91e3e0e1aba3.js",
    "38c63ba898531016d18a.js",
    "3bdfb1df616a2088c1e0.js",
    "3c90638fb88082924255.css",
    "3e84bcbcd7b696fc4bce.js",
    "3ed82418b90dc01f96ab.js",
    "41124400a83eb525bf08.css",
    "41447c85a721a262fdf3.css",
    "41930581842131e1a7b4.css",
    "4f3af7b1416f84e0993c.js",
    "519b514a5142cbcda7f2.css",
    "53b450142a73ee15f8c8.css",
    "5986e145044345e6c177.js",
    "60ca2f01a3bb42a37afd.js",
    "69a9310a23e4b5bdfce5.js",
    "6a4c5aaeb73cf6bcf55c.js",
    "6c26467d8747cadc9f72.js",
    "6ec4fc0ad7da175fbecb.js",
    "7acfd853541d5d7de088.css",
    "7e355d2b4c4b882de518.css",
    "84d4c5b761a621c85f48.js",
    "8f76b6a6cab17477c199.js",
    "9321f089468f18f11bcc.js",
    "97ed3fece637d1817c42.js",
    "9838e61d4d4339123f56.css",
    "9b5ac897b6e312ca3b3e.js",
    "9d8df1aaaebec64c8a4a.js",
    "a2ff013f19a2146052b0.css",
    "a8dc3cbaac32c132503f.css",
    "a9c17e539311cf11685b.js",
    "ab007b2500947025e7c1.css",
    "adcf20a20d1e87ecdf3e.css",
    "afe0bd625ff33229d8e2.js",
    "b7efb54a288f62fa5445.js",
    "b981d5fe45fdce2a6166.js",
    "cfa2799ae68d5b22093b.js",
    "d2fcb46e72676b04fa23.css",
    "dbcfad97392035709626.js",
    "de5e88fdeb5a0842cfa3.css",
    "e0b32861eb489a3140f8.js",
    "e7ff0adad236afbe0b9e.js",
    "e92bfdb268501f7326fc.js",
    "f5f07ee40fbcb9e9b140.css",
    "f9bbd441c58078122b28.js",
    "fbd0f0a2e9822524902b.js",
    "fc5064f3dcadd04e6c05.css",
    "fd04783ae2193ca97543.css",
    "fd9359542e040e7aa866.css",
    "ff54f688e77a167f7b9d.js"
  ],
  "modules": {
    "16020552": [
      8
    ],
    "17381640": [
      58,
      30
    ],
    "19790989": [
      15,
      14,
      67,
      67,
      68,
      67,
      67,
      68,
      67,
      67,
      67
    ],
    "23526558": [
      5,
      21
    ],
    "24323802": [
      8
    ],
    "28799264": [
      8
    ],
    "28960599": [
      6,
      34
    ],
    "31038510": [
      31,
      48
    ],
    "34225872": [
      8
    ],
    "39246421": [
      39,
      27
    ],
    "39793421": [
      8
    ],
    "44889592": [
      8
    ],
    "48206930": [
      2
    ],
    "49079356": [
      8
    ],
    "49923923": [
      61,
      35,
      72
    ],
    "52766248": [
      15,
      14,
      67,
      67,
      68,
      67,
      67,
      68,
      67,
      67,
      67
    ],
    "54101451": [
      6,
      34
    ],
    "55014696": [
      47,
      12
    ],
    "56507053": [
      8
    ],
    "75541611": [
      41
    ],
    "77427666": [
      15,
      14,
      67,
      67,
      68,
      67,
      67,
      68,
      67,
      67,
      67
    ],
    "93338926": [
      40
    ],
    "95630226": [
      39,
      27
    ],
    "7bef5f86": [
      8
    ],
    "34dc742a": [
      3,
      33,
      70,
      71,
      69,
      65,
      66
    ],
    "2290ca7e": [
      8
    ],
    "1ef10ad9": [
      8
    ],
    "649b1580": [
      8
    ],
    "1ce3608a": [
      8
    ],
    "62462cec": [
      8
    ],
    "c067ab5c": [
      8
    ],
    "b851b83c": [
      8
    ],
    "289fbbc8": [
      8
    ],
    "12f9513d": [
      8
    ],
    "46ecffc7": [
      8
    ],
    "6c4866c2": [
      8
    ],
    "708cf454": [
      8
    ],
    "99bd584a": [
      8
    ],
    "be3ca558": [
      8
    ],
    "184492a2": [
      8
    ],
    "6a1094c3": [
      3,
      33,
      70,
      71,
      69,
      65,
      66
    ],
    "5059cadc": [
      8
    ],
    "f7bca486": [
      8
    ],
    "1dae0fa9": [
      8
    ],
    "27baee86": [
      6,
      34
    ],
    "495f1e09": [
      8
    ],
    "378381ee": [
      6,
      34
    ],
    "c36d6a92": [
      8
    ],
    "08f5011f": [
      8
    ],
    "0b5eb6d4": [
      8
    ],
    "43e1d492": [
      8
    ],
    "0794db04": [
      8
    ],
    "6a29c6a0": [
      8
    ],
    "2c772de7": [
      8
    ],
    "903b9830": [
      8
    ],
    "1de03d96": [
      8
    ],
    "31ece7b7": [
      8
    ],
    "81e173d6": [
      3,
      33,
      70,
      71,
      69,
      65,
      66
    ],
    "0476a286": [
      3,
      33,
      70,
      71,
      69,
      65,
      66
    ],
    "10005c69": [
      3,
      33,
      70,
      71,
      69,
      65,
      66
    ],
    "2a492e0a": [
      3,
      33,
      70,
      71,
      69,
      65,
      66
    ],
    "a02af7a0": [
      3,
      33,
      70,
      71,
      69,
      65,
      66
    ],
    "5eafafce": [
      3,
      33,
      70,
      71,
      69,
      65,
      66
    ],
    "5a9eb99f": [
      3,
      33,
      70,
      71,
      69,
      65,
      66
    ],
    "b02edc4c": [
      3,
      33,
      70,
      71,
      69,
      65,
      66
    ],
    "6fa55dfa": [
      3,
      33,
      70,
      71,
      69,
      65,
      66
    ],
    "29efb376": [
      3,
      33,
      70,
      71,
      69,
      65,
      66
    ],
    "28799f23": [
      3,
      33,
      70,
      71,
      69,
      65,
      66
    ],
    "57b7d9b9": [
      3,
      33,
      70,
      71,
      69,
      65,
      66
    ],
    "58d3ecde": [
      3,
      33,
      70,
      71,
      69,
      65,
      66
    ],
    "34387db8": [
      3,
      33,
      70,
      71,
      69,
      65,
      66
    ],
    "470a3106": [
      3,
      33,
      70,
      71,
      69,
      65,
      66
    ],
    "7fe2555c": [
      3,
      33,
      70,
      71,
      69,
      65,
      66
    ],
    "3472bb12": [
      3,
      33,
      70,
      71,
      69,
      65,
      66
    ],
    "6ddaaf3a": [
      3,
      33,
      70,
      71,
      69,
      65,
      66
    ],
    "109ccb3d": [
      3,
      33,
      70,
      71,
      69,
      65,
      66
    ],
    "06d04ef8": [
      3,
      33,
      70,
      71,
      69,
      65,
      66
    ],
    "9d4724dc": [
      3,
      33,
      70,
      71,
      69,
      65,
      66
    ],
    "0e9124ee": [
      3,
      33,
      70,
      71,
      69,
      65,
      66
    ],
    "3f124487": [
      3,
      33,
      70,
      71,
      69,
      65,
      66
    ],
    "b77dcef0": [
      3,
      33,
      70,
      71,
      69,
      65,
      66
    ],
    "f25abd60": [
      3,
      33,
      70,
      71,
      69,
      65,
      66
    ],
    "738a7618": [
      3,
      33,
      70,
      71,
      69,
      65,
      66
    ],
    "63ed8bec": [
      3,
      33,
      70,
      71,
      69,
      65,
      66
    ],
    "4a733ac3": [
      3,
      33,
      70,
      71,
      69,
      65,
      66
    ],
    "68316a52": [
      3,
      33,
      70,
      71,
      69,
      65,
      66
    ],
    "0530d732": [
      3,
      33,
      70,
      71,
      69,
      65,
      66
    ],
    "0fcd0305": [
      3,
      33,
      70,
      71,
      69,
      65,
      66
    ],
    "31abb7a4": [
      3,
      33,
      70,
      71,
      69,
      65,
      66
    ],
    "58d2a772": [
      3,
      33,
      70,
      71,
      69,
      65,
      66
    ],
    "895b0536": [
      3,
      33,
      70,
      71,
      69,
      65,
      66
    ],
    "12d6350e": [
      3,
      33,
      70,
      71,
      69,
      65,
      66
    ],
    "79bf5a35": [
      3,
      33,
      70,
      71,
      69,
      65,
      66
    ],
    "3317038a": [
      3,
      33,
      70,
      71,
      69,
      65,
      66
    ],
    "63e7a6cd": [
      3,
      33,
      70,
      71,
      69,
      65,
      66
    ],
    "371e6c39": [
      3,
      33,
      70,
      71,
      69,
      65,
      66
    ],
    "64b26fa1": [
      3,
      33,
      70,
      71,
      69,
      65,
      66
    ],
    "0d12c2ce": [
      3,
      33,
      70,
      71,
      69,
      65,
      66
    ],
    "da55ac94": [
      3,
      33,
      70,
      71,
      69,
      65,
      66
    ],
    "224ccb1e": [
      3,
      33,
      70,
      71,
      69,
      65,
      66
    ],
    "ea587432": [
      3,
      33,
      70,
      71,
      69,
      65,
      66
    ],
    "5d3315f3": [
      3,
      33,
      70,
      71,
      69,
      65,
      66
    ],
    "7f9d19ea": [
      3,
      33,
      70,
      71,
      69,
      65,
      66
    ],
    "d9dd10ba": [
      3,
      33,
      70,
      71,
      69,
      65,
      66
    ],
    "2510eba6": [
      3,
      33,
      70,
      71,
      69,
      65,
      66
    ],
    "410c0626": [
      3,
      33,
      70,
      71,
      69,
      65,
      66
    ],
    "60daaf84": [
      3,
      33,
      70,
      71,
      69,
      65,
      66
    ],
    "c93837ba": [
      3,
      33,
      70,
      71,
      69,
      65,
      66
    ],
    "6a65638a": [
      3,
      33,
      70,
      71,
      69,
      65,
      66
    ],
    "7368c2ae": [
      3,
      33,
      70,
      71,
      69,
      65,
      66
    ],
    "4f805866": [
      3,
      33,
      70,
      71,
      69,
      65,
      66
    ],
    "805d7010": [
      3,
      33,
      70,
      71,
      69,
      65,
      66
    ],
    "679a51e4": [
      3,
      33,
      70,
      71,
      69,
      65,
      66
    ],
    "69ff26b8": [
      3,
      33,
      70,
      71,
      69,
      65,
      66
    ],
    "f02036dc": [
      8
    ],
    "68afdcf8": [
      8
    ],
    "e79b18ca": [
      8
    ],
    "4c8b888a": [
      8
    ],
    "7a0ad84a": [
      8
    ],
    "2d6acf03": [
      8
    ],
    "67d214f3": [
      8
    ],
    "99323b06": [
      8
    ],
    "0612395c": [
      8
    ],
    "95dc3ff4": [
      8
    ],
    "135afb42": [
      8
    ],
    "1aa4b4ac": [
      8
    ],
    "662080cc": [
      8
    ],
    "b22fa354": [
      8
    ],
    "5cc9b9db": [
      6,
      34
    ],
    "704a3bd2": [
      8
    ],
    "27d55bec": [
      8
    ],
    "49ebf498": [
      8
    ],
    "437462de": [
      8
    ],
    "2e67f1be": [
      8
    ],
    "3e425ebe": [
      8
    ],
    "ae91d00c": [
      8
    ],
    "41a186b9": [
      8
    ],
    "43091f5c": [
      8
    ],
    "87fcd754": [
      8
    ],
    "68c56b48": [
      8
    ],
    "7de46a9e": [
      8
    ],
    "aac2135e": [
      3,
      33,
      70,
      71,
      69,
      65,
      66
    ],
    "707a5a71": [
      6,
      34
    ],
    "0f3d782a": [
      6,
      34
    ],
    "633d3e4e": [
      6,
      34
    ],
    "64a54a8b": [
      6,
      34
    ],
    "223e4b59": [
      8
    ],
    "36b3229a": [
      8
    ],
    "73adb860": [
      8
    ],
    "93c6c9d0": [
      6,
      34
    ],
    "4f4b1f92": [
      8
    ],
    "75ab70dc": [
      8
    ],
    "a2a2a350": [
      8
    ],
    "e8e12bf6": [
      8
    ],
    "033415c9": [
      8
    ],
    "8fe1df4a": [
      8
    ],
    "7329a29a": [
      8
    ],
    "469f113c": [
      8
    ],
    "458c53df": [
      8
    ],
    "2650d824": [
      8
    ],
    "9fa0188a": [
      8
    ],
    "eb7294b0": [
      8
    ],
    "0bfeeaf4": [
      8
    ],
    "5323bf4b": [
      8
    ],
    "2ed55d3e": [
      8
    ],
    "1d3b6c96": [
      6,
      34
    ],
    "6780c25a": [
      8
    ],
    "e64d0170": [
      8
    ],
    "5505ef90": [
      8
    ],
    "5290333c": [
      6,
      34
    ],
    "76b6faee": [
      8
    ],
    "1c6c2376": [
      8
    ],
    "5b1e08c2": [
      8
    ],
    "d145a688": [
      8
    ],
    "f4307230": [
      6,
      34
    ],
    "618fb497": [
      8
    ],
    "c73d34a6": [
      8
    ],
    "71dd0c54": [
      8
    ],
    "1b3c3ca5": [
      8
    ],
    "518873b6": [
      8
    ],
    "524149ec": [
      8
    ],
    "7dc03ec5": [
      8
    ],
    "382ea5d7": [
      8
    ],
    "714ec8a8": [
      8
    ],
    "9b3da872": [
      8
    ],
    "0346eb9a": [
      8
    ],
    "725a299e": [
      8
    ],
    "25982b2e": [
      8
    ],
    "0b281815": [
      8
    ],
    "84fdce40": [
      8
    ],
    "4f3ed040": [
      8
    ],
    "5bd7c82c": [
      6,
      34
    ],
    "9cbc9e9c": [
      3,
      33,
      70,
      71,
      69,
      65,
      66
    ],
    "4997e241": [
      3,
      33,
      70,
      71,
      69,
      65,
      66
    ],
    "67d6064c": [
      3,
      33,
      70,
      71,
      69,
      65,
      66
    ],
    "8ca66a60": [
      3,
      33,
      70,
      71,
      69,
      65,
      66
    ],
    "124eec0c": [
      3,
      33,
      70,
      71,
      69,
      65,
      66
    ],
    "bbff7864": [
      3,
      33,
      70,
      71,
      69,
      65,
      66
    ],
    "da8e0682": [
      6,
      34
    ],
    "d51a40d2": [
      8
    ],
    "6246118d": [
      6,
      34
    ],
    "134af26a": [
      6,
      34
    ],
    "4713726d": [
      3,
      33,
      70,
      71,
      69,
      65,
      66
    ],
    "353c2fe4": [
      6,
      34
    ],
    "27159fe0": [
      8
    ],
    "c1a368ea": [
      8
    ],
    "7502e6cc": [
      8
    ],
    "0918bc64": [
      8
    ],
    "6af4f1df": [
      8
    ],
    "3c494e99": [
      8
    ],
    "b1022ef0": [
      8
    ],
    "5d85ea51": [
      8
    ],
    "915cfa24": [
      8
    ],
    "f6d3c45a": [
      8
    ],
    "23c67c88": [
      8
    ],
    "21c54ddc": [
      8
    ],
    "4fb3c953": [
      8
    ],
    "33da1f68": [
      8
    ],
    "31245b29": [
      8
    ],
    "1a44051a": [
      8
    ],
    "39b37922": [
      8
    ],
    "0a54b6ea": [
      8
    ],
    "20c00a95": [
      8
    ],
    "8d063528": [
      8
    ],
    "c1d611d0": [
      8
    ],
    "0d5b3550": [
      6,
      34
    ],
    "26a00c1e": [
      6,
      34
    ],
    "5b95a270": [
      6,
      34
    ],
    "e37fc42c": [
      8
    ],
    "7f251eae": [
      8
    ],
    "1eb497f2": [
      8
    ],
    "1d5bf332": [
      8
    ],
    "e3f4d372": [
      8
    ],
    "16cdfb99": [
      8
    ],
    "49e00457": [
      8
    ],
    "6290e0d7": [
      8
    ],
    "699ad88b": [
      8
    ],
    "fa7f95ea": [
      8
    ],
    "5de47e5d": [
      8
    ],
    "d148a256": [
      8
    ],
    "17808fd8": [
      6,
      34
    ],
    "35eabd21": [
      3,
      33,
      70,
      71,
      69,
      65,
      66
    ],
    "3464edc6": [
      6,
      34
    ],
    "1b57d34f": [
      8
    ],
    "63b2e976": [
      6,
      34
    ],
    "0c94ca58": [
      6,
      34
    ],
    "0974879c": [
      6,
      34
    ],
    "14e36d98": [
      6,
      34
    ],
    "391160f0": [
      6,
      34
    ],
    "6e4e5534": [
      6,
      34
    ],
    "5d02d07d": [
      6,
      34
    ],
    "4bc44350": [
      6,
      34
    ],
    "bf51aa46": [
      6,
      34
    ],
    "c132fbb6": [
      6,
      34
    ],
    "af632b70": [
      6,
      34
    ],
    "4da7dd1e": [
      6,
      34
    ],
    "5c92701c": [
      6,
      34
    ],
    "a727cdde": [
      8
    ],
    "f63969ca": [
      8
    ],
    "7e31f16a": [
      6,
      34
    ],
    "190b56fc": [
      3,
      33,
      70,
      71,
      69,
      65,
      66
    ],
    "7925457f": [
      8
    ],
    "6bdf2381": [
      6,
      34
    ],
    "a2ad6afa": [
      8
    ],
    "396222c2": [
      6,
      34
    ],
    "3588b158": [
      8
    ],
    "bb53081c": [
      8
    ],
    "0543fcc4": [
      8
    ],
    "ee8f15f2": [
      8
    ],
    "1ea6cb30": [
      8
    ],
    "118f154d": [
      8
    ],
    "1fe27d94": [
      8
    ],
    "5c6bca74": [
      8
    ],
    "5adf18ba": [
      8
    ],
    "e9aef05c": [
      8
    ],
    "3e0c6648": [
      8
    ],
    "80a369b6": [
      8
    ],
    "515a1746": [
      8
    ],
    "923465fc": [
      8
    ],
    "45314c70": [
      8
    ],
    "ad2a6e84": [
      8
    ],
    "8e3c3618": [
      8
    ],
    "1b6308f0": [
      8
    ],
    "21dc45a4": [
      8
    ],
    "ba2d8416": [
      8
    ],
    "3f27301c": [
      8
    ],
    "216a967e": [
      8
    ],
    "33bf8b67": [
      8
    ],
    "57ab753e": [
      8
    ],
    "da097df4": [
      8
    ],
    "7b03c40c": [
      8
    ],
    "667ab306": [
      8
    ],
    "d6237e2a": [
      8
    ],
    "8b08398a": [
      8
    ],
    "28ad2ba0": [
      8
    ],
    "119898e8": [
      8
    ],
    "574c3da8": [
      8
    ],
    "3ae2cc27": [
      8
    ],
    "bf4ffd54": [
      8
    ],
    "58ac7b04": [
      8
    ],
    "54b19f28": [
      8
    ],
    "02788ae1": [
      3,
      33,
      70,
      71,
      69,
      65,
      66
    ],
    "232ed3e6": [
      3,
      33,
      70,
      71,
      69,
      65,
      66
    ],
    "70a21894": [
      8
    ],
    "7a2d3130": [
      8
    ],
    "6473e1cc": [
      8
    ],
    "fddaac2e": [
      8
    ],
    "8271ebb8": [
      8
    ],
    "41216bff": [
      8
    ],
    "0cb42bde": [
      8
    ],
    "3deabac4": [
      8
    ],
    "e5b39972": [
      8
    ],
    "0d9ba714": [
      8
    ],
    "06b240c8": [
      8
    ],
    "c1c15914": [
      8
    ],
    "181ec3c0": [
      8
    ],
    "3e68d820": [
      8
    ],
    "f0ad8734": [
      8
    ],
    "628e9afc": [
      8
    ],
    "6c7de5f2": [
      6,
      34
    ],
    "09912f67": [
      6,
      34
    ],
    "9160a13e": [
      8
    ],
    "6007d0b6": [
      8
    ],
    "4b8fb890": [
      6,
      34
    ],
    "42e8e6cc": [
      3,
      33,
      70,
      71,
      69,
      65,
      66
    ],
    "340f05f5": [
      6,
      34
    ],
    "43cd2b83": [
      6,
      34
    ],
    "48c1e179": [
      8
    ],
    "4eb093f4": [
      6,
      34
    ],
    "e5cf3cc2": [
      3,
      33,
      70,
      71,
      69,
      65,
      66
    ],
    "648ef59b": [
      6,
      34
    ],
    "cd60acfa": [
      8
    ],
    "ce3cc56a": [
      8
    ],
    "4e47f239": [
      6,
      34
    ],
    "47ab1f68": [
      8
    ],
    "0a2eab31": [
      6,
      34
    ],
    "522f6694": [
      8
    ],
    "c97326a2": [
      8
    ],
    "60bfe5d5": [
      8
    ],
    "692eac28": [
      8
    ],
    "51ceae4b": [
      8
    ],
    "db1a2878": [
      8
    ],
    "a87c1992": [
      6,
      34
    ],
    "8a1ba95e": [
      6,
      34
    ],
    "9c742cca": [
      3,
      33,
      70,
      71,
      69,
      65,
      66
    ],
    "a2812b70": [
      3,
      33,
      70,
      71,
      69,
      65,
      66
    ],
    "f6c7cbf8": [
      8
    ],
    "f90b609e": [
      8
    ],
    "2797f4d8": [
      8
    ],
    "76774bd4": [
      8
    ],
    "d26812ca": [
      8
    ],
    "63160afa": [
      8
    ],
    "4a5fd8e7": [
      8
    ],
    "a513b390": [
      8
    ],
    "116a6aee": [
      8
    ],
    "2bcf3ca0": [
      8
    ],
    "f2113600": [
      8
    ],
    "c2ff1e64": [
      8
    ],
    "5acdc4f3": [
      8
    ],
    "1b4e554a": [
      8
    ],
    "710ec726": [
      8
    ],
    "7c8a4dea": [
      8
    ],
    "021b77f9": [
      8
    ],
    "4ed8b283": [
      8
    ],
    "09bdf3e9": [
      8
    ],
    "4582f8f8": [
      8
    ],
    "079714be": [
      3,
      33,
      70,
      71,
      69,
      65,
      66
    ],
    "bd2a7f04": [
      3,
      33,
      70,
      71,
      69,
      65,
      66
    ],
    "3b647de0": [
      3,
      33,
      70,
      71,
      69,
      65,
      66
    ],
    "6fdad5e3": [
      3,
      33,
      70,
      71,
      69,
      65,
      66
    ],
    "f778a290": [
      6,
      34
    ],
    "c31c7f80": [
      3,
      33,
      70,
      71,
      69,
      65,
      66
    ],
    "794fe019": [
      3,
      33,
      70,
      71,
      69,
      65,
      66
    ],
    "74146fd9": [
      6,
      34
    ],
    "443ceb28": [
      3,
      33,
      70,
      71,
      69,
      65,
      66
    ],
    "690d4f3c": [
      3,
      33,
      70,
      71,
      69,
      65,
      66
    ],
    "31b5538c": [
      3,
      33,
      70,
      71,
      69,
      65,
      66
    ],
    "8a1bfa08": [
      3,
      33,
      70,
      71,
      69,
      65,
      66
    ],
    "e7f3ac8e": [
      3,
      33,
      70,
      71,
      69,
      65,
      66
    ],
    "f7db5496": [
      3,
      33,
      70,
      71,
      69,
      65,
      66
    ],
    "3c110820": [
      3,
      33,
      70,
      71,
      69,
      65,
      66
    ],
    "0fde2fd4": [
      3,
      33,
      70,
      71,
      69,
      65,
      66
    ],
    "631f7686": [
      8
    ],
    "79f214d5": [
      8
    ],
    "4019849b": [
      8
    ],
    "76d19716": [
      8
    ],
    "a751d016": [
      8
    ],
    "2c6d6210": [
      8
    ],
    "521a2058": [
      8
    ],
    "801deb6e": [
      8
    ],
    "529bc9c9": [
      8
    ],
    "132da8e2": [
      8
    ],
    "7767231a": [
      8
    ],
    "01d9f5be": [
      8
    ],
    "2fea732c": [
      8
    ],
    "04366cd1": [
      8
    ],
    "584aa11e": [
      8
    ],
    "457a23c3": [
      6,
      34
    ],
    "c5f4c83e": [
      8
    ],
    "59ce58c5": [
      8
    ],
    "c12410ae": [
      8
    ],
    "3fb1385a": [
      8
    ],
    "8ee718da": [
      8
    ],
    "5468f4ff": [
      8
    ],
    "40a9d6f8": [
      8
    ],
    "6ff92622": [
      8
    ],
    "5cf59c06": [
      6,
      34
    ],
    "74131a9b": [
      8
    ],
    "3e89a910": [
      8
    ],
    "0d0d76a1": [
      8
    ],
    "63e3033f": [
      8
    ],
    "77611bb6": [
      8
    ],
    "6d27aaf4": [
      8
    ],
    "1a1d2419": [
      8
    ],
    "ccd2cbb0": [
      8
    ],
    "f37c0356": [
      8
    ],
    "22c72c6f": [
      8
    ],
    "361a4058": [
      6,
      34
    ],
    "b183fd5a": [
      8
    ],
    "e9a9265a": [
      8
    ],
    "45948bb9": [
      8
    ],
    "2635f530": [
      8
    ],
    "100538a8": [
      8
    ],
    "92c39db0": [
      8
    ],
    "628a0f46": [
      8
    ],
    "e02c4792": [
      8
    ],
    "72ea9b4d": [
      8
    ],
    "35ff3aa9": [
      8
    ],
    "4af1cde1": [
      6,
      34
    ],
    "c5b194f4": [
      6,
      34
    ],
    "7612e726": [
      6,
      34
    ],
    "3315c687": [
      6,
      34
    ],
    "011836d4": [
      6,
      34
    ],
    "5ef792f8": [
      6,
      34
    ],
    "22bb9b26": [
      6,
      34
    ],
    "451d3d84": [
      6,
      34
    ],
    "d13f9978": [
      6,
      34
    ],
    "58a61f76": [
      6,
      34
    ],
    "329dbaa1": [
      6,
      34
    ],
    "7f8dc96c": [
      6,
      34
    ],
    "4603b90a": [
      6,
      34
    ],
    "1e5bd63a": [
      6,
      34
    ],
    "98b85a5c": [
      6,
      34
    ],
    "98901eea": [
      6,
      34
    ],
    "4f66bd12": [
      6,
      34
    ],
    "6633bbb5": [
      6,
      34
    ],
    "b88e4652": [
      6,
      34
    ],
    "424da08c": [
      6,
      34
    ],
    "0efb01c8": [
      6,
      34
    ],
    "57b701cc": [
      6,
      34
    ],
    "b8f54fba": [
      6,
      34
    ],
    "ee04ed66": [
      6,
      34
    ],
    "465a79bc": [
      6,
      34
    ],
    "001d2e41": [
      6,
      34
    ],
    "0f76abc4": [
      6,
      34
    ],
    "e9a62db4": [
      6,
      34
    ],
    "b618b76e": [
      6,
      34
    ],
    "30f3994e": [
      6,
      34
    ],
    "78faf522": [
      6,
      34
    ],
    "06d275ca": [
      6,
      34
    ],
    "561d450b": [
      50
    ],
    "75e4eb41": [
      50
    ],
    "05b8358c": [
      50
    ],
    "56cda7a0": [
      23,
      64
    ],
    "f208b1ca": [
      23,
      64
    ],
    "3446bd06": [
      23,
      64
    ],
    "68ab797b": [
      23,
      64
    ],
    "02ac921b": [
      23,
      64
    ],
    "1b3e8ebb": [
      57
    ],
    "624ffbbc": [
      20,
      49
    ],
    "616c308e": [
      20,
      49
    ],
    "19dd5172": [
      20,
      49
    ],
    "255d5af7": [
      40
    ],
    "d1db1164": [
      61,
      35,
      72
    ],
    "8a554b0c": [
      61,
      35,
      72
    ],
    "53caaf66": [
      61,
      35,
      72
    ],
    "cd2c6942": [
      61,
      35,
      72
    ],
    "c5fbe6b4": [
      61,
      35,
      72
    ],
    "17d43285": [
      61,
      35,
      72
    ],
    "544abbbb": [
      61,
      35,
      72
    ],
    "5b1dbd9a": [
      61,
      35,
      72
    ],
    "1883ce78": [
      61,
      35,
      72
    ],
    "793aaf3a": [
      61,
      35,
      72
    ],
    "268ec2ab": [
      61,
      35,
      72
    ],
    "7d762209": [
      5,
      21
    ],
    "0982039d": [
      50
    ],
    "7d3eecf6": [
      5,
      21
    ],
    "2b386f2a": [
      5,
      21
    ],
    "84e3b2de": [
      5,
      21
    ],
    "02faf9fa": [
      5,
      21
    ],
    "02c2525e": [
      5,
      21
    ],
    "47ca4a80": [
      5,
      21
    ],
    "db89f504": [
      5,
      21
    ],
    "e2a4be22": [
      5,
      21
    ],
    "6580a23b": [
      5,
      21
    ],
    "69cb1fec": [
      5,
      21
    ],
    "edd36896": [
      5,
      21
    ],
    "8c66f85a": [
      32,
      26
    ],
    "37fe9cb6": [
      9,
      28
    ],
    "359ff562": [
      22,
      36
    ],
    "137ba8ff": [
      31,
      48
    ],
    "eb64388e": [
      31,
      48
    ],
    "8d4fe38e": [
      31,
      48
    ],
    "7b68bc5a": [
      31,
      48
    ],
    "7464d10a": [
      31,
      48
    ],
    "db4aa66a": [
      31,
      48
    ],
    "779abc54": [
      4,
      13
    ],
    "48cc639a": [
      11,
      53
    ],
    "da4bae30": [
      47,
      12
    ],
    "67cc51fb": [
      58,
      30
    ],
    "c4292d8a": [
      39,
      27
    ],
    "1576250f": [
      39,
      27
    ],
    "65cd8756": [
      39,
      27
    ],
    "2f18f2e2": [
      39,
      27
    ],
    "0d2664c0": [
      43,
      10
    ],
    "48ca86ca": [
      62,
      25
    ],
    "4d173f33": [
      63,
      56
    ],
    "252aa5e0": [
      54,
      45
    ],
    "1272b4b2": [
      15,
      14,
      67,
      67,
      68,
      67,
      67,
      68,
      67,
      67,
      67
    ],
    "6b703bde": [
      15,
      14,
      67,
      67,
      68,
      67,
      67,
      68,
      67,
      67,
      67
    ],
    "9a986580": [
      15,
      14,
      67,
      67,
      68,
      67,
      67,
      68,
      67,
      67,
      67
    ],
    "eb175760": [
      15,
      14,
      67,
      67,
      68,
      67,
      67,
      68,
      67,
      67,
      67
    ],
    "edb21754": [
      15,
      14,
      67,
      67,
      68,
      67,
      67,
      68,
      67,
      67,
      67
    ],
    "ced96c60": [
      15,
      14,
      67,
      67,
      68,
      67,
      67,
      68,
      67,
      67,
      67
    ],
    "4efba3bc": [
      15,
      14,
      67,
      67,
      68,
      67,
      67,
      68,
      67,
      67,
      67
    ],
    "4523493a": [
      15,
      14,
      67,
      67,
      68,
      67,
      67,
      68,
      67,
      67,
      67
    ],
    "40f49c36": [
      15,
      14,
      67,
      67,
      68,
      67,
      67,
      68,
      67,
      67,
      67
    ],
    "6d7af43a": [
      15,
      14,
      67,
      67,
      68,
      67,
      67,
      68,
      67,
      67,
      67
    ],
    "5751ebdb": [
      15,
      14,
      67,
      67,
      68,
      67,
      67,
      68,
      67,
      67,
      67
    ],
    "897dceac": [
      15,
      14,
      67,
      67,
      68,
      67,
      67,
      68,
      67,
      67,
      67
    ],
    "5cd13055": [
      15,
      14,
      67,
      67,
      68,
      67,
      67,
      68,
      67,
      67,
      67
    ],
    "41c33b12": [
      15,
      14,
      67,
      67,
      68,
      67,
      67,
      68,
      67,
      67,
      67
    ],
    "2e99705f": [
      61,
      35,
      72
    ],
    "4ad5eff1": [
      61,
      35,
      72
    ],
    "2b413bb7": [
      61,
      35,
      72
    ],
    "2c85c251": [
      61,
      35,
      72
    ],
    "0cb1de68": [
      61,
      35,
      72
    ],
    "1165cdea": [
      61,
      35,
      72
    ],
    "3f6e8166": [
      61,
      35,
      72
    ],
    "9014be40": [
      61,
      35,
      72
    ],
    "5910d81c": [
      61,
      35,
      72
    ],
    "7b1548f9": [
      61,
      35,
      72
    ],
    "8e3865d0": [
      61,
      35,
      72
    ],
    "5009c978": [
      61,
      35,
      72
    ],
    "64139a6d": [
      61,
      35,
      72
    ],
    "2be18f17": [
      61,
      35,
      72
    ],
    "d25f37e6": [
      61,
      35,
      72
    ],
    "b3b91730": [
      61,
      35,
      72
    ],
    "51e6efb0": [
      61,
      35,
      72
    ],
    "709a344b": [
      61,
      35,
      72
    ],
    "5f5156be": [
      61,
      35,
      72
    ],
    "2c61d2c7": [
      61,
      35,
      72
    ],
    "3938cc7f": [
      61,
      35,
      72
    ],
    "bf83c5d8": [
      61,
      35,
      72
    ],
    "676b871c": [
      61,
      35,
      72
    ],
    "9ae3dacc": [
      61,
      35,
      72
    ],
    "09223ee4": [
      61,
      35,
      72
    ],
    "1ac4931b": [
      61,
      35,
      72
    ],
    "00455da4": [
      61,
      35,
      72
    ],
    "ae38c048": [
      61,
      35,
      72
    ],
    "20a0cae7": [
      61,
      35,
      72
    ],
    "43f020be": [
      61,
      35,
      72
    ],
    "ee3d5a74": [
      61,
      35,
      72
    ],
    "75c488b2": [
      61,
      35,
      72
    ],
    "65281a32": [
      61,
      35,
      72
    ],
    "69090b86": [
      61,
      35,
      72
    ],
    "7bbe27b7": [
      61,
      35,
      72
    ],
    "b00df3f2": [
      61,
      35,
      72
    ],
    "005d3951": [
      61,
      35,
      72
    ],
    "4e30b864": [
      61,
      35,
      72
    ],
    "3cdf1820": [
      61,
      35,
      72
    ],
    "98c85f44": [
      61,
      35,
      72
    ],
    "2ab6a052": [
      61,
      35,
      72
    ],
    "0a6d761f": [
      61,
      35,
      72
    ],
    "b5e9a5c2": [
      61,
      35,
      72
    ],
    "a40be25c": [
      61,
      35,
      72
    ],
    "fe1830a2": [
      61,
      35,
      72
    ],
    "4b522ef8": [
      61,
      35,
      72
    ],
    "1f91a326": [
      61,
      35,
      72
    ],
    "5d0bf178": [
      61,
      35,
      72
    ],
    "a49ea032": [
      61,
      35,
      72
    ],
    "02509d47": [
      61,
      35,
      72
    ],
    "1255f5d3": [
      61,
      35,
      72
    ],
    "45a86734": [
      61,
      35,
      72
    ],
    "791aed9c": [
      61,
      35,
      72
    ],
    "8d1ad85c": [
      61,
      35,
      72
    ],
    "6c5f7070": [
      61,
      35,
      72
    ],
    "5feebd52": [
      61,
      35,
      72
    ],
    "b36458dc": [
      61,
      35,
      72
    ],
    "3be5e89e": [
      61,
      35,
      72
    ],
    "b1650e3a": [
      61,
      35,
      72
    ],
    "aaf266fe": [
      57
    ],
    "3bb4dd2e": [
      61,
      35,
      72
    ],
    "6b1bc1e0": [
      40
    ],
    "427ef621": [
      50
    ],
    "d1fae868": [
      40
    ],
    "3f628fc7": [
      40
    ],
    "67fbd117": [
      50
    ],
    "3bb062b4": [
      2
    ],
    "4c8355cf": [
      57
    ],
    "531260d8": [
      20,
      49
    ],
    "227f2fb6": [
      20,
      49
    ],
    "1030214a": [
      20,
      49
    ],
    "326d8eb2": [
      20,
      49
    ],
    "03ece76a": [
      20,
      49
    ],
    "e59a91ae": [
      20,
      49
    ],
    "4c8130fa": [
      20,
      49
    ],
    "2fa86edb": [
      20,
      49
    ],
    "72c89367": [
      20,
      49
    ],
    "172ddd75": [
      20,
      49
    ],
    "7dc5e54f": [
      40
    ],
    "6aa17676": [
      40
    ],
    "7ebd0412": [
      50
    ],
    "2f3af390": [
      61,
      35,
      72
    ],
    "959a7360": [
      61,
      35,
      72
    ],
    "3e648cc9": [
      61,
      35,
      72
    ],
    "10799d7c": [
      61,
      35,
      72
    ],
    "e968794a": [
      61,
      35,
      72
    ],
    "0d7505b6": [
      61,
      35,
      72
    ],
    "557b2970": [
      61,
      35,
      72
    ],
    "23c8f6cc": [
      61,
      35,
      72
    ],
    "73981b10": [
      61,
      35,
      72
    ],
    "68ecf7d6": [
      61,
      35,
      72
    ],
    "6ef65992": [
      5,
      21
    ],
    "2e7a9802": [
      40
    ],
    "4282cc36": [
      50
    ],
    "d392189a": [
      5,
      21
    ],
    "012b3cfd": [
      5,
      21
    ],
    "5754c9ba": [
      5,
      21
    ],
    "613c17d6": [
      5,
      21
    ],
    "1989c6f0": [
      5,
      21
    ],
    "18a9bb92": [
      5,
      21
    ],
    "67fc88ee": [
      40
    ],
    "c322480c": [
      40
    ],
    "456c92a8": [
      5,
      21
    ],
    "06004e43": [
      40
    ],
    "7ef9ff12": [
      40
    ],
    "2564d96b": [
      40
    ],
    "590621f8": [
      40
    ],
    "a0637bc4": [
      40
    ],
    "e04f58f2": [
      40
    ],
    "50368c79": [
      40
    ],
    "bf0ba2fe": [
      5,
      21
    ],
    "e574722e": [
      5,
      21
    ],
    "dcdf76cc": [
      5,
      21
    ],
    "a54af53a": [
      5,
      21
    ],
    "1e0f7fe5": [
      32,
      26
    ],
    "2d724f92": [
      9,
      28
    ],
    "4c6769f4": [
      22,
      36
    ],
    "73751d76": [
      18,
      7
    ],
    "95c34b6c": [
      18,
      7
    ],
    "66de4c11": [
      31,
      48
    ],
    "6a2b63d8": [
      18,
      7
    ],
    "d04c0194": [
      18,
      7
    ],
    "e0d7eb6a": [
      31,
      48
    ],
    "5cd6b9e7": [
      31,
      48
    ],
    "2dd57dfc": [
      18,
      7
    ],
    "b62b6ad8": [
      18,
      7
    ],
    "943ee910": [
      31,
      48
    ],
    "19303a8d": [
      31,
      48
    ],
    "5eb176dd": [
      31,
      48
    ],
    "43f18666": [
      4,
      13
    ],
    "08fbd805": [
      38
    ],
    "07a09922": [
      38
    ],
    "a11bf7e0": [
      38
    ],
    "8beafd36": [
      38
    ],
    "33d174a8": [
      38
    ],
    "1b3d7a76": [
      11,
      53
    ],
    "0b4afda9": [
      58,
      30
    ],
    "3382a31a": [
      39,
      27
    ],
    "4b51c98a": [
      39,
      27
    ],
    "601286e9": [
      39,
      27
    ],
    "d9dfd032": [
      39,
      27
    ],
    "b2140286": [
      39,
      27
    ],
    "3c066224": [
      43,
      10
    ],
    "3c3a3a10": [
      62,
      25
    ],
    "3e3201c5": [
      63,
      56
    ],
    "5768358e": [
      54,
      45
    ],
    "5e15a640": [
      15,
      14,
      67,
      67,
      68,
      67,
      67,
      68,
      67,
      67,
      67
    ],
    "ee6b4b82": [
      15,
      14,
      67,
      67,
      68,
      67,
      67,
      68,
      67,
      67,
      67
    ],
    "7136456e": [
      15,
      14,
      67,
      67,
      68,
      67,
      67,
      68,
      67,
      67,
      67
    ],
    "e08b0a3c": [
      15,
      14,
      67,
      67,
      68,
      67,
      67,
      68,
      67,
      67,
      67
    ],
    "2ca5a004": [
      15,
      14,
      67,
      67,
      68,
      67,
      67,
      68,
      67,
      67,
      67
    ],
    "64ea13e2": [
      15,
      14,
      67,
      67,
      68,
      67,
      67,
      68,
      67,
      67,
      67
    ],
    "cbeb562c": [
      15,
      14,
      67,
      67,
      68,
      67,
      67,
      68,
      67,
      67,
      67
    ],
    "5beabdcc": [
      15,
      14,
      67,
      67,
      68,
      67,
      67,
      68,
      67,
      67,
      67
    ],
    "57bc10c8": [
      15,
      14,
      67,
      67,
      68,
      67,
      67,
      68,
      67,
      67,
      67
    ],
    "1df0aade": [
      15,
      14,
      67,
      67,
      68,
      67,
      67,
      68,
      67,
      67,
      67
    ],
    "65e4b388": [
      15,
      14,
      67,
      67,
      68,
      67,
      67,
      68,
      67,
      67,
      67
    ],
    "1ef84e03": [
      15,
      14,
      67,
      67,
      68,
      67,
      67,
      68,
      67,
      67,
      67
    ],
    "5beea325": [
      15,
      14,
      67,
      67,
      68,
      67,
      67,
      68,
      67,
      67,
      67
    ],
    "7574a714": [
      52,
      17
    ],
    "ea711fe2": [
      52,
      17
    ],
    "a200bdca": [
      2
    ],
    "d4febacc": [
      2
    ],
    "50d001c6": [
      2
    ],
    "0e09706a": [
      19,
      37
    ],
    "ee61c17e": [
      19,
      37
    ],
    "caf08470": [
      51
    ],
    "14f272cd": [
      19,
      37
    ],
    "0454551e": [
      15,
      14,
      67,
      67,
      68,
      67,
      67,
      68,
      67,
      67,
      67
    ],
    "6f52e2b9": [
      15,
      14,
      67,
      67,
      68,
      67,
      67,
      68,
      67,
      67,
      67
    ],
    "e90cb3d0": [
      15,
      14,
      67,
      67,
      68,
      67,
      67,
      68,
      67,
      67,
      67
    ],
    "32748d19": [
      15,
      14,
      67,
      67,
      68,
      67,
      67,
      68,
      67,
      67,
      67
    ],
    "7065066d": [
      15,
      14,
      67,
      67,
      68,
      67,
      67,
      68,
      67,
      67,
      67
    ],
    "109bd019": [
      15,
      14,
      67,
      67,
      68,
      67,
      67,
      68,
      67,
      67,
      67
    ],
    "5d3f0538": [
      15,
      14,
      67,
      67,
      68,
      67,
      67,
      68,
      67,
      67,
      67
    ],
    "212d27b2": [
      15,
      14,
      67,
      67,
      68,
      67,
      67,
      68,
      67,
      67,
      67
    ],
    "375ebb67": [
      15,
      14,
      67,
      67,
      68,
      67,
      67,
      68,
      67,
      67,
      67
    ],
    "7ab29a86": [
      15,
      14,
      67,
      67,
      68,
      67,
      67,
      68,
      67,
      67,
      67
    ],
    "0ba1cae7": [
      15,
      14,
      67,
      67,
      68,
      67,
      67,
      68,
      67,
      67,
      67
    ],
    "06962da3": [
      15,
      14,
      67,
      67,
      68,
      67,
      67,
      68,
      67,
      67,
      67
    ],
    "0075f2d1": [
      15,
      14,
      67,
      67,
      68,
      67,
      67,
      68,
      67,
      67,
      67
    ],
    "1039438a": [
      15,
      14,
      67,
      67,
      68,
      67,
      67,
      68,
      67,
      67,
      67
    ],
    "60a4ab7e": [
      15,
      14,
      67,
      67,
      68,
      67,
      67,
      68,
      67,
      67,
      67
    ],
    "cc849308": [
      15,
      14,
      67,
      67,
      68,
      67,
      67,
      68,
      67,
      67,
      67
    ],
    "54a930a1": [
      15,
      14,
      67,
      67,
      68,
      67,
      67,
      68,
      67,
      67,
      67
    ],
    "129dc1bd": [
      15,
      14,
      67,
      67,
      68,
      67,
      67,
      68,
      67,
      67,
      67
    ],
    "869c145a": [
      15,
      14,
      67,
      67,
      68,
      67,
      67,
      68,
      67,
      67,
      67
    ],
    "6ae13d7e": [
      15,
      14,
      67,
      67,
      68,
      67,
      67,
      68,
      67,
      67,
      67
    ],
    "1596a55b": [
      15,
      14,
      67,
      67,
      68,
      67,
      67,
      68,
      67,
      67,
      67
    ],
    "0cfa316f": [
      15,
      14,
      67,
      67,
      68,
      67,
      67,
      68,
      67,
      67,
      67
    ],
    "9056f4e4": [
      15,
      14,
      67,
      67,
      68,
      67,
      67,
      68,
      67,
      67,
      67
    ],
    "1ec33226": [
      15,
      14,
      67,
      67,
      68,
      67,
      67,
      68,
      67,
      67,
      67
    ],
    "54b7eb75": [
      15,
      14,
      67,
      67,
      68,
      67,
      67,
      68,
      67,
      67,
      67
    ],
    "44f1c7d9": [
      15,
      14,
      67,
      67,
      68,
      67,
      67,
      68,
      67,
      67,
      67
    ],
    "88e4c53e": [
      15,
      14,
      67,
      67,
      68,
      67,
      67,
      68,
      67,
      67,
      67
    ],
    "76f537ad": [
      15,
      14,
      67,
      67,
      68,
      67,
      67,
      68,
      67,
      67,
      67
    ],
    "b3f9bcfe": [
      15,
      14,
      67,
      67,
      68,
      67,
      67,
      68,
      67,
      67,
      67
    ],
    "12459a1a": [
      15,
      14,
      67,
      67,
      68,
      67,
      67,
      68,
      67,
      67,
      67
    ],
    "600cc8dd": [
      15,
      14,
      67,
      67,
      68,
      67,
      67,
      68,
      67,
      67,
      67
    ],
    "2f1a487a": [
      15,
      14,
      67,
      67,
      68,
      67,
      67,
      68,
      67,
      67,
      67
    ],
    "4c5037ad": [
      15,
      14,
      67,
      67,
      68,
      67,
      67,
      68,
      67,
      67,
      67
    ],
    "1854fd47": [
      15,
      14,
      67,
      67,
      68,
      67,
      67,
      68,
      67,
      67,
      67
    ],
    "b9723592": [
      15,
      14,
      67,
      67,
      68,
      67,
      67,
      68,
      67,
      67,
      67
    ],
    "d0c9f1a8": [
      15,
      14,
      67,
      67,
      68,
      67,
      67,
      68,
      67,
      67,
      67
    ],
    "1b35e665": [
      15,
      14,
      67,
      67,
      68,
      67,
      67,
      68,
      67,
      67,
      67
    ],
    "75a05c5a": [
      15,
      14,
      67,
      67,
      68,
      67,
      67,
      68,
      67,
      67,
      67
    ],
    "4b457e39": [
      15,
      14,
      67,
      67,
      68,
      67,
      67,
      68,
      67,
      67,
      67
    ],
    "f5dc300c": [
      15,
      14,
      67,
      67,
      68,
      67,
      67,
      68,
      67,
      67,
      67
    ],
    "1e3d99fe": [
      15,
      14,
      67,
      67,
      68,
      67,
      67,
      68,
      67,
      67,
      67
    ],
    "c4092d5c": [
      15,
      14,
      67,
      67,
      68,
      67,
      67,
      68,
      67,
      67,
      67
    ],
    "58e9f833": [
      15,
      14,
      67,
      67,
      68,
      67,
      67,
      68,
      67,
      67,
      67
    ],
    "138235da": [
      15,
      14,
      67,
      67,
      68,
      67,
      67,
      68,
      67,
      67,
      67
    ],
    "9c62b08a": [
      15,
      14,
      67,
      67,
      68,
      67,
      67,
      68,
      67,
      67,
      67
    ],
    "cf504df8": [
      15,
      14,
      67,
      67,
      68,
      67,
      67,
      68,
      67,
      67,
      67
    ],
    "40829f2e": [
      15,
      14,
      67,
      67,
      68,
      67,
      67,
      68,
      67,
      67,
      67
    ],
    "f25a2110": [
      15,
      14,
      67,
      67,
      68,
      67,
      67,
      68,
      67,
      67,
      67
    ],
    "3c65f456": [
      15,
      14,
      67,
      67,
      68,
      67,
      67,
      68,
      67,
      67,
      67
    ],
    "754e50ae": [
      15,
      14,
      67,
      67,
      68,
      67,
      67,
      68,
      67,
      67,
      67
    ],
    "5dc861fe": [
      15,
      14,
      67,
      67,
      68,
      67,
      67,
      68,
      67,
      67,
      67
    ],
    "5229c978": [
      15,
      14,
      67,
      67,
      68,
      67,
      67,
      68,
      67,
      67,
      67
    ],
    "f09a183e": [
      15,
      14,
      67,
      67,
      68,
      67,
      67,
      68,
      67,
      67,
      67
    ],
    "7579eff0": [
      15,
      14,
      67,
      67,
      68,
      67,
      67,
      68,
      67,
      67,
      67
    ],
    "97517b06": [
      15,
      14,
      67,
      67,
      68,
      67,
      67,
      68,
      67,
      67,
      67
    ],
    "3270ad64": [
      15,
      14,
      67,
      67,
      68,
      67,
      67,
      68,
      67,
      67,
      67
    ],
    "beca9d66": [
      15,
      14,
      67,
      67,
      68,
      67,
      67,
      68,
      67,
      67,
      67
    ],
    "16a9cad2": [
      15,
      14,
      67,
      67,
      68,
      67,
      67,
      68,
      67,
      67,
      67
    ],
    "1187cf97": [
      15,
      14,
      67,
      67,
      68,
      67,
      67,
      68,
      67,
      67,
      67
    ],
    "7ba5c4fe": [
      15,
      14,
      67,
      67,
      68,
      67,
      67,
      68,
      67,
      67,
      67
    ],
    "05fe3005": [
      15,
      14,
      67,
      67,
      68,
      67,
      67,
      68,
      67,
      67,
      67
    ],
    "b4f1c644": [
      15,
      14,
      67,
      67,
      68,
      67,
      67,
      68,
      67,
      67,
      67
    ],
    "ff6b8ece": [
      15,
      14,
      67,
      67,
      68,
      67,
      67,
      68,
      67,
      67,
      67
    ],
    "5156cbcf": [
      15,
      14,
      67,
      67,
      68,
      67,
      67,
      68,
      67,
      67,
      67
    ],
    "42ae8821": [
      15,
      14,
      67,
      67,
      68,
      67,
      67,
      68,
      67,
      67,
      67
    ],
    "8f6d98fc": [
      15,
      14,
      67,
      67,
      68,
      67,
      67,
      68,
      67,
      67,
      67
    ],
    "7194fdb4": [
      15,
      14,
      67,
      67,
      68,
      67,
      67,
      68,
      67,
      67,
      67
    ],
    "f109c6b0": [
      15,
      14,
      67,
      67,
      68,
      67,
      67,
      68,
      67,
      67,
      67
    ],
    "3dd9e189": [
      15,
      14,
      67,
      67,
      68,
      67,
      67,
      68,
      67,
      67,
      67
    ],
    "f2e50c48": [
      5,
      21
    ],
    "568ff133": [
      5,
      21
    ],
    "c35b9acc": [
      5,
      21
    ],
    "02156b93": [
      5,
      21
    ],
    "633b606f": [
      5,
      21
    ],
    "07374f30": [
      5,
      21
    ],
    "887f5430": [
      5,
      21
    ],
    "154b964c": [
      5,
      21
    ],
    "c782f616": [
      5,
      21
    ],
    "b7ec28d2": [
      5,
      21
    ],
    "41dec036": [
      5,
      21
    ],
    "6da3a05a": [
      5,
      21
    ],
    "451b88da": [
      5,
      21
    ],
    "45c5fa06": [
      5,
      21
    ],
    "7e68524b": [
      5,
      21
    ],
    "6bd75ee8": [
      5,
      21
    ],
    "cea4226e": [
      5,
      21
    ],
    "38b4859a": [
      5,
      21
    ],
    "785a3c71": [
      5,
      21
    ],
    "5cbb8bc2": [
      5,
      21
    ],
    "5e058176": [
      5,
      21
    ],
    "09202506": [
      5,
      21
    ],
    "0ae7bea6": [
      5,
      21
    ],
    "06a3221e": [
      5,
      21
    ],
    "0779981f": [
      5,
      21
    ],
    "0e7f61fa": [
      5,
      21
    ],
    "26cb5b3a": [
      5,
      21
    ],
    "142bcf1b": [
      5,
      21
    ],
    "5a9a682a": [
      5,
      21
    ],
    "6f2dc3d2": [
      5,
      21
    ],
    "1aeb5f2e": [
      5,
      21
    ],
    "606539e5": [
      5,
      21
    ],
    "66b693de": [
      5,
      21
    ],
    "6011f0ac": [
      5,
      21
    ],
    "2ad9a0e5": [
      5,
      21
    ],
    "2320a1c8": [
      5,
      21
    ],
    "478819e6": [
      5,
      21
    ],
    "69d777f4": [
      5,
      21
    ],
    "75ba827f": [
      5,
      21
    ],
    "41d4e1ac": [
      5,
      21
    ],
    "02708e42": [
      5,
      21
    ],
    "7488d3c6": [
      5,
      21
    ],
    "36a1f5e2": [
      5,
      21
    ],
    "57725f2b": [
      5,
      21
    ],
    "28d98a8a": [
      5,
      21
    ],
    "2434cfa0": [
      5,
      21
    ],
    "cc0b5d1c": [
      5,
      21
    ],
    "6a5c60d4": [
      5,
      21
    ],
    "fe261024": [
      5,
      21
    ],
    "49c3e0c8": [
      5,
      21
    ],
    "9699b058": [
      5,
      21
    ],
    "5e32018b": [
      5,
      21
    ],
    "111665c2": [
      5,
      21
    ],
    "423011d0": [
      5,
      21
    ],
    "cf61c206": [
      5,
      21
    ],
    "94cbcd94": [
      5,
      21
    ],
    "614442f9": [
      5,
      21
    ],
    "495ef9fc": [
      5,
      21
    ],
    "417583ae": [
      5,
      21
    ],
    "f38d46bc": [
      31,
      48
    ],
    "17f24835": [
      31,
      48
    ],
    "93db035c": [
      31,
      48
    ],
    "2d8079d5": [
      31,
      48
    ],
    "dd71dfc6": [
      31,
      48
    ],
    "563c9c54": [
      31,
      48
    ],
    "22ec015c": [
      31,
      48
    ],
    "289c21ae": [
      31,
      48
    ],
    "2cb289c4": [
      31,
      48
    ],
    "246e7bc0": [
      31,
      48
    ],
    "7f795dbc": [
      31,
      48
    ],
    "8977b964": [
      31,
      48
    ],
    "03e9ea69": [
      31,
      48
    ],
    "ff1e7880": [
      31,
      48
    ],
    "4af2ff26": [
      31,
      48
    ],
    "63aff510": [
      31,
      48
    ],
    "6d939540": [
      31,
      48
    ],
    "d1c833de": [
      31,
      48
    ],
    "5ed023d8": [
      31,
      48
    ],
    "2d672d64": [
      31,
      48
    ],
    "1e09d644": [
      31,
      48
    ],
    "124f1ad4": [
      31,
      48
    ],
    "6d424f2b": [
      31,
      48
    ],
    "22271fc3": [
      31,
      48
    ],
    "78c89422": [
      31,
      48
    ],
    "a9c21eb8": [
      31,
      48
    ],
    "2734fb6b": [
      31,
      48
    ],
    "fa5efe6a": [
      31,
      48
    ],
    "05489ce4": [
      31,
      48
    ],
    "30b5ad94": [
      39,
      27
    ],
    "1667e1f2": [
      39,
      27
    ],
    "698e1980": [
      39,
      27
    ],
    "ddf7dd32": [
      39,
      27
    ],
    "56969ad5": [
      39,
      27
    ],
    "679008e2": [
      39,
      27
    ],
    "2d37fc34": [
      39,
      27
    ],
    "08ad10ac": [
      39,
      27
    ],
    "c321f632": [
      39,
      27
    ],
    "98980a80": [
      39,
      27
    ],
    "3e921758": [
      39,
      27
    ],
    "0b0ebaff": [
      39,
      27
    ],
    "e61c41e4": [
      39,
      27
    ],
    "095bb616": [
      39,
      27
    ],
    "6f9fcac8": [
      39,
      27
    ],
    "da21bc00": [
      39,
      27
    ],
    "2e8e95c0": [
      39,
      27
    ],
    "a6084fae": [
      39,
      27
    ],
    "61bf7c9f": [
      39,
      27
    ],
    "da89cf4e": [
      39,
      27
    ],
    "4adf4094": [
      39,
      27
    ],
    "746cdad3": [
      39,
      27
    ],
    "6423cba0": [
      39,
      27
    ],
    "8bc8e210": [
      39,
      27
    ],
    "a384e024": [
      20,
      49
    ],
    "0859d545": [
      20,
      49
    ],
    "2901e6f0": [
      20,
      49
    ],
    "2f2b90b6": [
      20,
      49
    ],
    "1ad4191d": [
      20,
      49
    ],
    "2fd32240": [
      20,
      49
    ],
    "61dc88ba": [
      20,
      49
    ],
    "b7b82dd4": [
      20,
      49
    ],
    "221cb9cc": [
      20,
      49
    ],
    "56ff1c2a": [
      20,
      49
    ],
    "b1c3b64c": [
      20,
      49
    ],
    "456d1746": [
      20,
      49
    ],
    "fba46b4c": [
      20,
      49
    ],
    "d8022aae": [
      20,
      49
    ],
    "29b8019b": [
      20,
      49
    ],
    "511b4ad3": [
      20,
      49
    ],
    "57de1ddd": [
      20,
      49
    ],
    "6b098daa": [
      32,
      26
    ],
    "3fd500c4": [
      32,
      26
    ],
    "5065e54a": [
      32,
      26
    ],
    "b5815d84": [
      32,
      26
    ],
    "28a27215": [
      32,
      26
    ],
    "0664d263": [
      32,
      26
    ],
    "50537c58": [
      32,
      26
    ],
    "279e4471": [
      32,
      26
    ],
    "b6c41410": [
      32,
      26
    ],
    "25f311fc": [
      32,
      26
    ],
    "6093fdfc": [
      9,
      28
    ],
    "6430ebd3": [
      9,
      28
    ],
    "37f4c5f8": [
      9,
      28
    ],
    "2641f51a": [
      9,
      28
    ],
    "63ad62fa": [
      9,
      28
    ],
    "71a228f9": [
      22,
      36
    ],
    "6d49699e": [
      22,
      36
    ],
    "0244629b": [
      22,
      36
    ],
    "1da5c4d1": [
      22,
      36
    ],
    "00993026": [
      22,
      36
    ],
    "9a09c32a": [
      4,
      13
    ],
    "d8237644": [
      4,
      13
    ],
    "0083beae": [
      4,
      13
    ],
    "ad071304": [
      4,
      13
    ],
    "4a1a9b18": [
      4,
      13
    ],
    "75b3e8ae": [
      41
    ],
    "279b138a": [
      41
    ],
    "76ff4886": [
      41
    ],
    "407cefdb": [
      41
    ],
    "408e860a": [
      11,
      53
    ],
    "70a7b378": [
      11,
      53
    ],
    "b10daaac": [
      11,
      53
    ],
    "1bf69fe4": [
      11,
      53
    ],
    "b4640f96": [
      11,
      53
    ],
    "5743c3cf": [
      47,
      12
    ],
    "afd48d48": [
      47,
      12
    ],
    "e60b23f2": [
      47,
      12
    ],
    "45cb1888": [
      47,
      12
    ],
    "593f51dc": [
      47,
      12
    ],
    "d283ecbc": [
      58,
      30
    ],
    "ebba0840": [
      58,
      30
    ],
    "120e8c94": [
      58,
      30
    ],
    "426b1569": [
      58,
      30
    ],
    "945d62b6": [
      59
    ],
    "0588ae8d": [
      59
    ],
    "576bd831": [
      59
    ],
    "318efe26": [
      59
    ],
    "25d1ad46": [
      59
    ],
    "2c211ae8": [
      44,
      16
    ],
    "efd4be1a": [
      44,
      16
    ],
    "03022664": [
      44,
      16
    ],
    "e255795a": [
      44,
      16
    ],
    "65cba13a": [
      44,
      16
    ],
    "0f84e938": [
      44,
      24
    ],
    "097c29f4": [
      44,
      24
    ],
    "78f6805c": [
      44,
      24
    ],
    "02018d66": [
      44,
      24
    ],
    "dbbffb32": [
      44,
      24
    ],
    "6d3999b0": [
      44,
      60
    ],
    "18feef62": [
      44,
      60
    ],
    "4b53c4ce": [
      44,
      60
    ],
    "288542af": [
      44,
      60
    ],
    "1798a8a3": [
      44,
      60
    ],
    "a34608b2": [
      43,
      10
    ],
    "5e0e2d47": [
      43,
      10
    ],
    "6e8410ef": [
      43,
      10
    ],
    "64cdcfa7": [
      43,
      10
    ],
    "3d1f5384": [
      43,
      10
    ],
    "b9f44f9e": [
      62,
      25
    ],
    "36c78203": [
      62,
      25
    ],
    "570782a5": [
      62,
      25
    ],
    "1322773a": [
      62,
      25
    ],
    "4b15603a": [
      62,
      25
    ],
    "7037c1ec": [
      63,
      56
    ],
    "74c50c45": [
      63,
      56
    ],
    "3bb412aa": [
      63,
      56
    ],
    "3b683436": [
      63,
      56
    ],
    "17d7b596": [
      63,
      56
    ],
    "dd6ecf1a": [
      46,
      55
    ],
    "2464bbec": [
      46,
      55
    ],
    "2958bc3e": [
      46,
      55
    ],
    "230eabaa": [
      46,
      55
    ],
    "790176ec": [
      46,
      55
    ],
    "12ba16c7": [
      54,
      45
    ],
    "354ed0e7": [
      54,
      45
    ],
    "1276a10f": [
      54,
      45
    ],
    "78a32b47": [
      54,
      45
    ],
    "6618dfe4": [
      54,
      45
    ],
    "45a877f4": [
      52,
      17
    ],
    "140ad262": [
      52,
      17
    ],
    "519afe86": [
      52,
      17
    ],
    "177b2108": [
      52,
      17
    ],
    "d3a2fd44": [
      6,
      34
    ],
    "aa1ed3ee": [
      6,
      34
    ],
    "1967465e": [
      6,
      34
    ],
    "0fbac8e0": [
      6,
      34
    ],
    "74d01f7e": [
      3,
      33,
      70,
      71,
      69,
      65,
      66
    ],
    "590d3bd8": [
      3,
      33,
      70,
      71,
      69,
      65,
      66
    ],
    "4b828544": [
      3,
      33,
      70,
      71,
      69,
      65,
      66
    ],
    "dce0e5ce": [
      3,
      33,
      70,
      71,
      69,
      65,
      66
    ],
    "50564a6b": [
      6,
      34
    ],
    "aaa2abba": [
      15,
      14,
      67,
      67,
      68,
      67,
      67,
      68,
      67,
      67,
      67
    ],
    "02ba453e": [
      5,
      21
    ],
    "145bb0b2": [
      32,
      26
    ],
    "a2adb30e": [
      9,
      28
    ],
    "678a636c": [
      43,
      10
    ],
    "144b1976": [
      62,
      25
    ],
    "e5f8e7f2": [
      63,
      56
    ],
    "3a7018e8": [
      54,
      45
    ],
    "b97f5394": [
      22,
      36
    ],
    "54b93c9f": [
      31,
      48
    ],
    "39f94c28": [
      4,
      13
    ],
    "493a2f07": [
      11,
      53
    ],
    "4d743ad8": [
      47,
      12
    ],
    "1b9b10b2": [
      58,
      30
    ],
    "71e6f13b": [
      39,
      27
    ],
    "37c02df3": [
      20,
      49
    ],
    "5af1d9a4": [
      15,
      14,
      67,
      67,
      68,
      67,
      67,
      68,
      67,
      67,
      67
    ],
    "a2d605ec": [
      15,
      14,
      67,
      67,
      68,
      67,
      67,
      68,
      67,
      67,
      67
    ],
    "138d1a02": [
      15,
      14,
      67,
      67,
      68,
      67,
      67,
      68,
      67,
      67,
      67
    ],
    "603b037e": [
      15,
      14,
      67,
      67,
      68,
      67,
      67,
      68,
      67,
      67,
      67
    ],
    "551cc924": [
      15,
      14,
      67,
      67,
      68,
      67,
      67,
      68,
      67,
      67,
      67
    ],
    "53bb4cbd": [
      15,
      14,
      67,
      67,
      68,
      67,
      67,
      68,
      67,
      67,
      67
    ],
    "3c2737ec": [
      15,
      14,
      67,
      67,
      68,
      67,
      67,
      68,
      67,
      67,
      67
    ],
    "c833c144": [
      15,
      14,
      67,
      67,
      68,
      67,
      67,
      68,
      67,
      67,
      67
    ],
    "78f414e2": [
      15,
      14,
      67,
      67,
      68,
      67,
      67,
      68,
      67,
      67,
      67
    ],
    "b9862bfe": [
      15,
      14,
      67,
      67,
      68,
      67,
      67,
      68,
      67,
      67,
      67
    ],
    "9a78abe4": [
      15,
      14,
      67,
      67,
      68,
      67,
      67,
      68,
      67,
      67,
      67
    ],
    "73bc4f30": [
      15,
      14,
      67,
      67,
      68,
      67,
      67,
      68,
      67,
      67,
      67
    ],
    "9e68370c": [
      3,
      33,
      70,
      71,
      69,
      65,
      66
    ],
    "d4165f58": [
      5,
      21
    ],
    "7062b332": [
      5,
      21
    ],
    "09613a2a": [
      5,
      21
    ],
    "4cad08d7": [
      5,
      21
    ],
    "6cb97a5a": [
      31,
      48
    ],
    "7bf5314f": [
      31,
      48
    ],
    "2b2e8765": [
      5,
      21
    ],
    "59b00d65": [
      20,
      49
    ],
    "640e8f98": [
      5,
      21
    ],
    "16c75296": [
      5,
      21
    ],
    "3751ba32": [
      39,
      27
    ],
    "2010d23a": [
      39,
      27
    ],
    "8195d9ae": [
      39,
      27
    ],
    "ca347944": [
      18,
      7
    ],
    "43ef7562": [
      20,
      49
    ],
    "8571c812": [
      20,
      49
    ],
    "61249e14": [
      20,
      49
    ],
    "5faad0ac": [
      20,
      49
    ],
    "32941bbc": [
      52,
      17
    ],
    "12d59c9f": [
      19,
      37
    ],
    "00a38d7b": [
      20,
      49
    ],
    "ce0611a2": [
      20,
      49
    ],
    "4982c3af": [
      20,
      49
    ],
    "2450aafc": [
      31,
      48
    ],
    "4af1bbe2": [
      61,
      35,
      72
    ],
    "455132da": [
      61,
      35,
      72
    ],
    "6b01e60a": [
      61,
      35,
      72
    ],
    "5f545f19": [
      61,
      35,
      72
    ],
    "1c21cd4f": [
      61,
      35,
      72
    ],
    "46ea1a46": [
      61,
      35,
      72
    ],
    "e7edac2c": [
      61,
      35,
      72
    ],
    "550a8b99": [
      61,
      35,
      72
    ],
    "0397a8a2": [
      61,
      35,
      72
    ],
    "872b9f22": [
      61,
      35,
      72
    ],
    "192e2136": [
      61,
      35,
      72
    ],
    "c484b4f2": [
      15,
      14,
      67,
      67,
      68,
      67,
      67,
      68,
      67,
      67,
      67
    ],
    "54f6588d": [
      31,
      48
    ],
    "43be33e5": [
      31,
      48
    ],
    "5804293f": [
      5,
      21
    ],
    "33a78bc3": [
      5,
      21
    ],
    "1bc48831": [
      5,
      21
    ],
    "6cb2eab8": [
      3,
      33,
      70,
      71,
      69,
      65,
      66
    ],
    "710ee7ae": [
      3,
      33,
      70,
      71,
      69,
      65,
      66
    ],
    "5ea6b5a4": [
      3,
      33,
      70,
      71,
      69,
      65,
      66
    ],
    "5fc411e7": [
      5,
      21
    ],
    "38de72f6": [
      6,
      34
    ],
    "54bfc380": [
      6,
      34
    ],
    "09204170": [
      6,
      34
    ],
    "60fc63fe": [
      6,
      34
    ]
  },
  "assetsMapping": {
    "167d78ad99424d98b51e.js": "bba68bf6",
    "21cf505805bdc654e891.js": "3f3a307c",
    "2514654ede1fd9e104e0.js": "0859c165",
    "2a3522d2a15d9e7fd931.js": "4d63c1da",
    "364512dc91e3e0e1aba3.js": "9d3e967c",
    "38c63ba898531016d18a.js": "5a2803a8",
    "3bdfb1df616a2088c1e0.js": "2a130dde",
    "3e84bcbcd7b696fc4bce.js": "58d3a99b",
    "3ed82418b90dc01f96ab.js": "bba68bf6",
    "4f3af7b1416f84e0993c.js": "37ae2162",
    "5986e145044345e6c177.js": "58d3b817",
    "60ca2f01a3bb42a37afd.js": "1297f864",
    "69a9310a23e4b5bdfce5.js": "0f680f67",
    "6a4c5aaeb73cf6bcf55c.js": "198e89e9",
    "6c26467d8747cadc9f72.js": "0526360e",
    "6c47a4814f024403dcf8.js": "6fca0322",
    "6ec4fc0ad7da175fbecb.js": "6cc1d1d6",
    "806d72eacac364467d2e.js": "1a3ae26b",
    "82762eab4e0b76c824cd.js": "7ea1d828",
    "84d4c5b761a621c85f48.js": "0304d928",
    "8f76b6a6cab17477c199.js": "0037b176",
    "9321f089468f18f11bcc.js": "bba68bf6",
    "97ed3fece637d1817c42.js": "841cc9ac",
    "9b5ac897b6e312ca3b3e.js": "5b84318c",
    "9d8df1aaaebec64c8a4a.js": "47c0d8aa",
    "a9c17e539311cf11685b.js": "6ca808ba",
    "afe0bd625ff33229d8e2.js": "1cb3f55f",
    "b7efb54a288f62fa5445.js": "0a0987a1",
    "b981d5fe45fdce2a6166.js": "92dbc39a",
    "cfa2799ae68d5b22093b.js": "bba68bf6",
    "dbcfad97392035709626.js": "489181f2",
    "e0b32861eb489a3140f8.js": "0da4b670",
    "e7ff0adad236afbe0b9e.js": "6693f307",
    "e92bfdb268501f7326fc.js": "38afbc48",
    "f9bbd441c58078122b28.js": "32c3a158",
    "fbd0f0a2e9822524902b.js": "0e708eca",
    "ff54f688e77a167f7b9d.js": "08ca5cf8"
  }
}